tgsdl/__init__.py
tgsdl/tgsdl.py
tgsdl-1.0.6.dist-info/LICENSE
tgsdl-1.0.6.dist-info/METADATA
tgsdl-1.0.6.dist-info/WHEEL
tgsdl-1.0.6.dist-info/entry_points.txt
tgsdl-1.0.6.dist-info/top_level.txt
tgsdl-1.0.6.dist-info/RECORD
