Metadata-Version: 2.1
Name: tgsdl
Version: 1.0.6
Summary: Telegram Sticker Pack Downloader Library
Home-page: https://github.com/lillisfeb/TGSDL/
Author: Bevlill
Author-email: voidlillis@gmail.com
License: MIT
Keywords: telegram,bot,sticker,download,stickerpack
Classifier: Programming Language :: Python :: 3
Classifier: License :: OSI Approved :: MIT License
Classifier: Operating System :: OS Independent
License-File: LICENSE
Requires-Dist: requests
Requires-Dist: colorclip
